ec2_compare/__init__.py
ec2_compare/data.py
ec2_compare/mixin.py
ec2_compare/utils.py
ec2_compare/internal/__init__.py
ec2_compare/internal/ec2data.py
ec2_compare/internal/ec2keys.py
ec2_compare/internal/architectures/__init__.py
ec2_compare/internal/architectures/arm64.py
ec2_compare/internal/architectures/i386.py
ec2_compare/internal/architectures/x86_64.py
ec2_compare/internal/auto_recovery/__init__.py
ec2_compare/internal/auto_recovery/false.py
ec2_compare/internal/auto_recovery/true.py
ec2_compare/internal/bare_metal/__init__.py
ec2_compare/internal/bare_metal/false.py
ec2_compare/internal/bare_metal/true.py
ec2_compare/internal/burstable_performance/__init__.py
ec2_compare/internal/burstable_performance/false.py
ec2_compare/internal/burstable_performance/true.py
ec2_compare/internal/current_generation/__init__.py
ec2_compare/internal/current_generation/false.py
ec2_compare/internal/current_generation/true.py
ec2_compare/internal/dedicated_hosts/__init__.py
ec2_compare/internal/dedicated_hosts/false.py
ec2_compare/internal/dedicated_hosts/true.py
ec2_compare/internal/ebs_optimized_support/__init__.py
ec2_compare/internal/ebs_optimized_support/default.py
ec2_compare/internal/ebs_optimized_support/supported.py
ec2_compare/internal/ebs_optimized_support/unsupported.py
ec2_compare/internal/ena_support/__init__.py
ec2_compare/internal/ena_support/required.py
ec2_compare/internal/ena_support/supported.py
ec2_compare/internal/ena_support/unsupported.py
ec2_compare/internal/encryption_support/__init__.py
ec2_compare/internal/encryption_support/supported.py
ec2_compare/internal/encryption_support/unsupported.py
ec2_compare/internal/free_tier_eligible/__init__.py
ec2_compare/internal/free_tier_eligible/false.py
ec2_compare/internal/free_tier_eligible/true.py
ec2_compare/internal/hibernation/__init__.py
ec2_compare/internal/hibernation/false.py
ec2_compare/internal/hibernation/true.py
ec2_compare/internal/hypervisor/__init__.py
ec2_compare/internal/hypervisor/nitro.py
ec2_compare-1.0.0a9.dist-info/LICENSE
ec2_compare-1.0.0a9.dist-info/METADATA
ec2_compare-1.0.0a9.dist-info/WHEEL
ec2_compare-1.0.0a9.dist-info/top_level.txt
ec2_compare-1.0.0a9.dist-info/RECORD
