Metadata-Version: 2.1
Name: ec2-compare
Version: 1.0.0a9
Summary: Compare EC2 instances families without querying AWS API
Home-page: https://github.com/weldpua2008/aws.ec2.compare
Author: Valeriys Soloviov
Author-email: weldpua2008@users.noreply.github.com
License: Apache License, Version 2.0
Platform: UNKNOWN
Classifier: Environment :: Console
Classifier: Intended Audience :: Information Technology
Classifier: Intended Audience :: System Administrators
Classifier: License :: OSI Approved :: Apache Software License
Classifier: Operating System :: POSIX :: Linux
Classifier: Operating System :: MacOS
Classifier: Operating System :: Microsoft :: Windows
Classifier: Programming Language :: Python
Classifier: Programming Language :: Python :: 3
Classifier: Programming Language :: Python :: 3.6
Classifier: Programming Language :: Python :: 3.7
Classifier: Programming Language :: Python :: 3.8
Classifier: Programming Language :: Python :: 3.9
Classifier: Typing :: Typed
Classifier: Topic :: Software Development :: Libraries :: Python Modules
Provides-Extra: devel
Requires-Dist: pytest ; extra == 'devel'
Requires-Dist: pytest-cov ; extra == 'devel'
Requires-Dist: flake8 ; extra == 'devel'
Requires-Dist: gitpython ; extra == 'devel'
Requires-Dist: pylint ; extra == 'devel'
Requires-Dist: mypy (==0.790) ; extra == 'devel'
Provides-Extra: git
Requires-Dist: gitpython ; extra == 'git'
